{"type":1,"letters":"FILORSST","words":[{"word":"FOSSIL","awardCoins":true},{"word":"FLORIST","awardCoins":false},{"word":"LIST","awardCoins":false},{"word":"FOR","awardCoins":false},{"word":"FLORISTS","awardCoins":false},{"word":"ITS","awardCoins":false},{"word":"FIRST","awardCoins":false},{"word":"SORT","awardCoins":false},{"word":"LOT","awardCoins":false},{"word":"SLOTS","awardCoins":false},{"word":"LOSS","awardCoins":false},{"word":"OIL","awardCoins":false}],"id":"b20e3b5e7b2f75d1e4a758d7508785d5"}