{"type":1,"letters":"AEELNRTX","words":[{"word":"EXTERNAL","awardCoins":false},{"word":"RELATE","awardCoins":false},{"word":"EXTRA","awardCoins":false},{"word":"NEXT","awardCoins":false},{"word":"ARE","awardCoins":false},{"word":"ETERNAL","awardCoins":false},{"word":"REAL","awardCoins":false},{"word":"ART","awardCoins":false},{"word":"NEXTEL","awardCoins":false},{"word":"ALERT","awardCoins":false},{"word":"RATE","awardCoins":false},{"word":"TAX","awardCoins":false}],"id":"d2402dadb362907fab3f4c9d51ec3dac"}