{"type":1,"letters":"AEGINST","words":[{"word":"SEATING","awardCoins":true},{"word":"STAGE","awardCoins":false},{"word":"SITE","awardCoins":false},{"word":"GET","awardCoins":false},{"word":"AGENTS","awardCoins":false},{"word":"GATES","awardCoins":false},{"word":"SIGN","awardCoins":false},{"word":"ITS","awardCoins":false},{"word":"GIANTS","awardCoins":false},{"word":"SATIN","awardCoins":false},{"word":"EAST","awardCoins":false},{"word":"SET","awardCoins":false}],"id":"ccfa95950fed4ecc77c37a7dc8abb040"}