{"type":1,"letters":"EHNORSTU","words":[{"word":"SOUTHERN","awardCoins":false},{"word":"SOUTH","awardCoins":false},{"word":"THEN","awardCoins":false},{"word":"NOT","awardCoins":false},{"word":"OTHERS","awardCoins":false},{"word":"HOUSE","awardCoins":false},{"word":"USER","awardCoins":false},{"word":"OUR","awardCoins":false},{"word":"HUNTER","awardCoins":false},{"word":"HOURS","awardCoins":false},{"word":"NOTE","awardCoins":false},{"word":"ONE","awardCoins":false}],"id":"795761459f2cd4090cfa38c2be32e94d"}