{"type":1,"letters":"ACHMOST","words":[{"word":"STOMACH","awardCoins":true},{"word":"MATCH","awardCoins":false},{"word":"MOST","awardCoins":false},{"word":"HAS","awardCoins":false},{"word":"THOMAS","awardCoins":false},{"word":"HOT","awardCoins":false},{"word":"CHAOS","awardCoins":false},{"word":"ACT","awardCoins":false},{"word":"COST","awardCoins":false},{"word":"COM","awardCoins":false},{"word":"CHAT","awardCoins":false},{"word":"SAT","awardCoins":false}],"id":"806d92ccaa6d7682d92b8175e7868d44"}