{"type":1,"letters":"AEEGMSSS","words":[{"word":"MESSAGES","awardCoins":false},{"word":"GAMES","awardCoins":false},{"word":"SAME","awardCoins":false},{"word":"SEE","awardCoins":false},{"word":"MESSAGE","awardCoins":false},{"word":"AGE","awardCoins":false},{"word":"SEEMS","awardCoins":false},{"word":"GAME","awardCoins":false},{"word":"GAS","awardCoins":false},{"word":"SAGEM","awardCoins":false},{"word":"MASS","awardCoins":false},{"word":"SEA","awardCoins":false}],"id":"2357e5aeb6eec069b086b898e86e9a2c"}