{"type":1,"letters":"CEMMNOST","words":[{"word":"COMMENTS","awardCoins":false},{"word":"MOMENT","awardCoins":false},{"word":"SOME","awardCoins":false},{"word":"NOT","awardCoins":false},{"word":"COMMENT","awardCoins":false},{"word":"NOTES","awardCoins":false},{"word":"MOST","awardCoins":false},{"word":"ONE","awardCoins":false},{"word":"MOMENTS","awardCoins":false},{"word":"COMES","awardCoins":false},{"word":"NOTE","awardCoins":false},{"word":"SET","awardCoins":false}],"id":"5853a0f4228ab35a2ad6237b63bda3c9"}