{"type":1,"letters":"DDEIOPRV","words":[{"word":"PROVIDED","awardCoins":false},{"word":"PERIOD","awardCoins":false},{"word":"VIDEO","awardCoins":false},{"word":"OVER","awardCoins":false},{"word":"DID","awardCoins":false},{"word":"PROVIDE","awardCoins":false},{"word":"PREV","awardCoins":false},{"word":"RED","awardCoins":false},{"word":"PROVED","awardCoins":false},{"word":"DRIVE","awardCoins":false},{"word":"DROP","awardCoins":false},{"word":"PRO","awardCoins":false}],"id":"9b35cd227d9b92d622047b1c8c82dffa"}