{"type":1,"letters":"AEGINOPRS","words":[{"word":"SINGAPORE","awardCoins":false},{"word":"SPRING","awardCoins":false},{"word":"PAGES","awardCoins":false},{"word":"PAGE","awardCoins":false},{"word":"ARE","awardCoins":false},{"word":"PERSIAN","awardCoins":false},{"word":"SIGN","awardCoins":false},{"word":"ONE","awardCoins":false},{"word":"SENIOR","awardCoins":false},{"word":"SPAIN","awardCoins":false},{"word":"OPEN","awardCoins":false},{"word":"AIR","awardCoins":false},{"word":"PRISON","awardCoins":false}],"id":"eb2b9b771b906dd45391e376a995ec75"}