{"type":1,"letters":"CDEIPRSTU","words":[{"word":"DISPUTE","awardCoins":true},{"word":"STUPID","awardCoins":false},{"word":"SITE","awardCoins":false},{"word":"USE","awardCoins":false},{"word":"PICTURES","awardCoins":false},{"word":"PICTURE","awardCoins":false},{"word":"SCRIPT","awardCoins":false},{"word":"SUPER","awardCoins":false},{"word":"USED","awardCoins":false},{"word":"ITS","awardCoins":false},{"word":"PREDICT","awardCoins":false},{"word":"SET","awardCoins":false},{"word":"PRICED","awardCoins":false}],"id":"b6eb999aed0eac8e01a73f04fb3a8af5"}